process_model_repair_algorithm.py
pm4py_model_repair-0.1.7.dist-info/METADATA
pm4py_model_repair-0.1.7.dist-info/WHEEL
pm4py_model_repair-0.1.7.dist-info/top_level.txt
pm4py_model_repair-0.1.7.dist-info/RECORD
